[
    {
        "card_name": ".Placeholder",
        "number": 89,
        "shape": "normal",
        "set": "INTR-EART",
        "position": "12"
    },
    {
        "card_name": "e"
    },
    {
        "card_name": "e"
    },
    {
        "card_name": "e"
    },
    {
        "card_name": "e"
    },
    {
        "card_name": "er"
    },
    {
        "card_name": "er"
    },
    {
        "card_name": "er"
    },
    {
        "card_name": "er"
    },
    {
        "card_name": "er"
    }
]